odoo10_addon_hr_timesheet_sheet_restrict_project-10.0.1.0.1-nspkg.pth
odoo/addons/hr_timesheet_sheet_restrict_project/README.rst
odoo/addons/hr_timesheet_sheet_restrict_project/__init__.py
odoo/addons/hr_timesheet_sheet_restrict_project/__manifest__.py
odoo/addons/hr_timesheet_sheet_restrict_project/i18n/hr_timesheet_sheet_restrict_project.pot
odoo/addons/hr_timesheet_sheet_restrict_project/models/__init__.py
odoo/addons/hr_timesheet_sheet_restrict_project/models/account_analytic_line.py
odoo/addons/hr_timesheet_sheet_restrict_project/static/description/icon.png
odoo/addons/hr_timesheet_sheet_restrict_project/static/src/js/restrict_timesheet.js
odoo/addons/hr_timesheet_sheet_restrict_project/views/hr_timesheet_restrict_project.xml
odoo/addons/hr_timesheet_sheet_restrict_project/views/hr_timesheet_sheet_view.xml
odoo10_addon_hr_timesheet_sheet_restrict_project-10.0.1.0.1.dist-info/METADATA
odoo10_addon_hr_timesheet_sheet_restrict_project-10.0.1.0.1.dist-info/WHEEL
odoo10_addon_hr_timesheet_sheet_restrict_project-10.0.1.0.1.dist-info/namespace_packages.txt
odoo10_addon_hr_timesheet_sheet_restrict_project-10.0.1.0.1.dist-info/top_level.txt
odoo10_addon_hr_timesheet_sheet_restrict_project-10.0.1.0.1.dist-info/RECORD
