Metadata-Version: 2.1
Name: odoo10-addon-hr-timesheet-sheet-restrict-project
Version: 10.0.1.0.1
Summary: Allows to restrict the analytic accounts that can be used in timesheets
Home-page: https://github.com/OCA/hr-timesheet
Author: Eficent, Odoo Community Association (OCA)
Author-email: support@odoo-community.org
License: LGPL-3
Platform: UNKNOWN
Classifier: Programming Language :: Python
Classifier: Framework :: Odoo
Classifier: License :: OSI Approved :: GNU Lesser General Public License v3 (LGPLv3)
Requires-Python: ~=2.7
Requires-Dist: odoo (<10.1dev,>=10.0)
